__init__.py
run_part.py
llm_partial_run-0.1.0.dist-info/METADATA
llm_partial_run-0.1.0.dist-info/WHEEL
llm_partial_run-0.1.0.dist-info/top_level.txt
llm_partial_run-0.1.0.dist-info/RECORD
