Metadata-Version: 2.1
Name: llm-partial-run
Version: 0.1.0
Summary: Microlib for partial deployment of LLMs
Author-email: Hristo Vrigazov <hvrigazov@gmail.com>
Project-URL: Homepage, https://github.com/microlib-org/llm_microlibs/llm_partial_run
Classifier: License :: OSI Approved :: MIT License
Classifier: Programming Language :: Python
Classifier: Programming Language :: Python :: 3
Requires-Python: >=3.8
Requires-Dist: socket-rpc
Requires-Dist: llm-weights-mmap
Provides-Extra: dev
Requires-Dist: pytest ; extra == 'dev'
Requires-Dist: tqdm ; extra == 'dev'
